<?xml version="1.0"?>
<opencv_storage>
<stage17>
  <maxWeakCount>3</maxWeakCount>
  <stageThreshold>-5.3166872262954712e-01</stageThreshold>
  <weakClassifiers>
    <_>
      <internalNodes>
        0 -1 10045 208588452 -1524568407 -1342249420 1256715872
        -948600873 -2091417602 1020665085 1692464486</internalNodes>
      <leafValues>
        -6.6666668653488159e-01 1.</leafValues></_>
    <_>
      <internalNodes>
        0 -1 29840 138412064 268501012 17 -2097151744 9 1090519040 2
        1403670658</internalNodes>
      <leafValues>
        -7.4240064620971680e-01 8.9522767066955566e-01</leafValues></_>
    <_>
      <internalNodes>
        0 -1 3516 1082306568 -2080368640 1 151060481 268472449 679477248
        264192 573474</internalNodes>
      <leafValues>
        -7.6022970676422119e-01 8.8483607769012451e-01</leafValues></_></weakClassifiers></stage17>
</opencv_storage>
